dataregistry/DataRegistry.py
dataregistry/__init__.py
dataregistry/_version.py
dataregistry/db_basic.py
dataregistry/exceptions.py
dataregistry/git_util.py
dataregistry/query.py
dataregistry/registrar/__init__.py
dataregistry/registrar/base_table_class.py
dataregistry/registrar/dataset.py
dataregistry/registrar/dataset_alias.py
dataregistry/registrar/dataset_util.py
dataregistry/registrar/execution.py
dataregistry/registrar/keyword.py
dataregistry/registrar/registrar.py
dataregistry/registrar/registrar_util.py
dataregistry/schema/__init__.py
dataregistry/schema/default_namespace.yaml
dataregistry/schema/keywords.yaml
dataregistry/schema/load_schema.py
dataregistry/schema/schema.yaml
dataregistry/schema/schema_version.py
dataregistry/site_config/site_rootdir.yaml
dataregistry_cli/cli.py
dataregistry_cli/delete.py
dataregistry_cli/modify.py
dataregistry_cli/query.py
dataregistry_cli/register.py
dataregistry_cli/show.py
lsstdesc_dataregistry-1.5.1.dist-info/licenses/LICENSE
lsstdesc_dataregistry-1.5.1.dist-info/METADATA
lsstdesc_dataregistry-1.5.1.dist-info/WHEEL
lsstdesc_dataregistry-1.5.1.dist-info/entry_points.txt
lsstdesc_dataregistry-1.5.1.dist-info/top_level.txt
lsstdesc_dataregistry-1.5.1.dist-info/RECORD
