Metadata-Version: 2.4
Name: lsstdesc-dataregistry
Version: 1.5.1
Summary: Creation and user API for DESC data registry.
Author-email: Joanne Bogart <jrb@slac.stanford.edu>, Stuart McAlpine <stuart.mcalpine@fysik.su.se>
Keywords: desc,python,registry
Classifier: Programming Language :: Python :: 3
Classifier: Programming Language :: Python :: 3.9
Classifier: Programming Language :: Python :: 3.10
Classifier: Programming Language :: Python :: 3.11
Classifier: Programming Language :: Python :: 3.12
Classifier: Programming Language :: Python :: 3.13
Requires-Python: >=3.9
License-File: LICENSE
Requires-Dist: psycopg2
Requires-Dist: sqlalchemy>=2.0.16
Requires-Dist: pyyaml
Requires-Dist: pandas
Provides-Extra: docs
Requires-Dist: sphinx_rtd_theme; extra == "docs"
Requires-Dist: myst_parser; extra == "docs"
Dynamic: license-file
